aind_metadata_utils/__init__.py
aind_metadata_utils/data_assets.py
aind_metadata_utils-0.1.2.dist-info/licenses/LICENSE
aind_metadata_utils-0.1.2.dist-info/METADATA
aind_metadata_utils-0.1.2.dist-info/WHEEL
aind_metadata_utils-0.1.2.dist-info/top_level.txt
aind_metadata_utils-0.1.2.dist-info/RECORD
