Metadata-Version: 2.4
Name: aind-metadata-utils
Version: 0.1.2
Summary: Generated from aind-library-template
Author: Allen Institute for Neural Dynamics
License: MIT
Classifier: Programming Language :: Python :: 3
Requires-Python: >=3.10
License-File: LICENSE
Dynamic: license-file
